{
	"backtraceGraph" : 
	{
		"commands" : 
		[
			"INSTALL",
			"absl_cc_library",
			"install"
		],
		"files" : 
		[
			"/home/dong/drone_kkk_ws/build/px4/_deps/abseil-cpp-src/CMake/AbseilHelpers.cmake",
			"/home/dong/drone_kkk_ws/build/px4/_deps/abseil-cpp-src/absl/strings/CMakeLists.txt"
		],
		"nodes" : 
		[
			{
				"file" : 1
			},
			{
				"command" : 1,
				"file" : 1,
				"line" : 17,
				"parent" : 0
			},
			{
				"command" : 0,
				"file" : 0,
				"line" : 224,
				"parent" : 1
			},
			{
				"command" : 2,
				"file" : 0,
				"line" : 349,
				"parent" : 1
			},
			{
				"command" : 1,
				"file" : 1,
				"line" : 35,
				"parent" : 0
			},
			{
				"command" : 0,
				"file" : 0,
				"line" : 224,
				"parent" : 4
			},
			{
				"command" : 2,
				"file" : 0,
				"line" : 349,
				"parent" : 4
			},
			{
				"command" : 1,
				"file" : 1,
				"line" : 96,
				"parent" : 0
			},
			{
				"command" : 0,
				"file" : 0,
				"line" : 224,
				"parent" : 7
			},
			{
				"command" : 1,
				"file" : 1,
				"line" : 109,
				"parent" : 0
			},
			{
				"command" : 0,
				"file" : 0,
				"line" : 224,
				"parent" : 9
			},
			{
				"command" : 1,
				"file" : 1,
				"line" : 122,
				"parent" : 0
			},
			{
				"command" : 0,
				"file" : 0,
				"line" : 224,
				"parent" : 11
			},
			{
				"command" : 2,
				"file" : 0,
				"line" : 349,
				"parent" : 11
			},
			{
				"command" : 1,
				"file" : 1,
				"line" : 470,
				"parent" : 0
			},
			{
				"command" : 0,
				"file" : 0,
				"line" : 224,
				"parent" : 14
			},
			{
				"command" : 1,
				"file" : 1,
				"line" : 488,
				"parent" : 0
			},
			{
				"command" : 0,
				"file" : 0,
				"line" : 224,
				"parent" : 16
			},
			{
				"command" : 2,
				"file" : 0,
				"line" : 349,
				"parent" : 16
			},
			{
				"command" : 1,
				"file" : 1,
				"line" : 683,
				"parent" : 0
			},
			{
				"command" : 0,
				"file" : 0,
				"line" : 224,
				"parent" : 19
			},
			{
				"command" : 2,
				"file" : 0,
				"line" : 349,
				"parent" : 19
			},
			{
				"command" : 1,
				"file" : 1,
				"line" : 721,
				"parent" : 0
			},
			{
				"command" : 0,
				"file" : 0,
				"line" : 224,
				"parent" : 22
			},
			{
				"command" : 1,
				"file" : 1,
				"line" : 748,
				"parent" : 0
			},
			{
				"command" : 0,
				"file" : 0,
				"line" : 224,
				"parent" : 24
			},
			{
				"command" : 2,
				"file" : 0,
				"line" : 349,
				"parent" : 24
			},
			{
				"command" : 1,
				"file" : 1,
				"line" : 777,
				"parent" : 0
			},
			{
				"command" : 0,
				"file" : 0,
				"line" : 224,
				"parent" : 27
			},
			{
				"command" : 1,
				"file" : 1,
				"line" : 792,
				"parent" : 0
			},
			{
				"command" : 0,
				"file" : 0,
				"line" : 224,
				"parent" : 29
			},
			{
				"command" : 2,
				"file" : 0,
				"line" : 349,
				"parent" : 29
			},
			{
				"command" : 1,
				"file" : 1,
				"line" : 827,
				"parent" : 0
			},
			{
				"command" : 0,
				"file" : 0,
				"line" : 224,
				"parent" : 32
			},
			{
				"command" : 2,
				"file" : 0,
				"line" : 349,
				"parent" : 32
			},
			{
				"command" : 1,
				"file" : 1,
				"line" : 897,
				"parent" : 0
			},
			{
				"command" : 0,
				"file" : 0,
				"line" : 224,
				"parent" : 35
			},
			{
				"command" : 2,
				"file" : 0,
				"line" : 349,
				"parent" : 35
			},
			{
				"command" : 1,
				"file" : 1,
				"line" : 936,
				"parent" : 0
			},
			{
				"command" : 0,
				"file" : 0,
				"line" : 224,
				"parent" : 38
			},
			{
				"command" : 1,
				"file" : 1,
				"line" : 969,
				"parent" : 0
			},
			{
				"command" : 0,
				"file" : 0,
				"line" : 224,
				"parent" : 40
			},
			{
				"command" : 2,
				"file" : 0,
				"line" : 349,
				"parent" : 40
			}
		]
	},
	"installers" : 
	[
		{
			"backtrace" : 2,
			"component" : "Unspecified",
			"destination" : "lib/pkgconfig",
			"paths" : 
			[
				"/home/dong/drone_kkk_ws/build/px4/lib/pkgconfig/absl_string_view.pc"
			],
			"type" : "file"
		},
		{
			"backtrace" : 3,
			"component" : "Unspecified",
			"destination" : "lib",
			"paths" : 
			[
				"_deps/abseil-cpp-build/absl/strings/libabsl_string_view.a"
			],
			"targetId" : "string_view::@cadd5db28f0587d4097f",
			"targetIndex" : 250,
			"type" : "target"
		},
		{
			"backtrace" : 5,
			"component" : "Unspecified",
			"destination" : "lib/pkgconfig",
			"paths" : 
			[
				"/home/dong/drone_kkk_ws/build/px4/lib/pkgconfig/absl_strings.pc"
			],
			"type" : "file"
		},
		{
			"backtrace" : 6,
			"component" : "Unspecified",
			"destination" : "lib",
			"paths" : 
			[
				"_deps/abseil-cpp-build/absl/strings/libabsl_strings.a"
			],
			"targetId" : "strings::@cadd5db28f0587d4097f",
			"targetIndex" : 251,
			"type" : "target"
		},
		{
			"backtrace" : 8,
			"component" : "Unspecified",
			"destination" : "lib/pkgconfig",
			"paths" : 
			[
				"/home/dong/drone_kkk_ws/build/px4/lib/pkgconfig/absl_charset.pc"
			],
			"type" : "file"
		},
		{
			"backtrace" : 10,
			"component" : "Unspecified",
			"destination" : "lib/pkgconfig",
			"paths" : 
			[
				"/home/dong/drone_kkk_ws/build/px4/lib/pkgconfig/absl_has_ostream_operator.pc"
			],
			"type" : "file"
		},
		{
			"backtrace" : 12,
			"component" : "Unspecified",
			"destination" : "lib/pkgconfig",
			"paths" : 
			[
				"/home/dong/drone_kkk_ws/build/px4/lib/pkgconfig/absl_strings_internal.pc"
			],
			"type" : "file"
		},
		{
			"backtrace" : 13,
			"component" : "Unspecified",
			"destination" : "lib",
			"paths" : 
			[
				"_deps/abseil-cpp-build/absl/strings/libabsl_strings_internal.a"
			],
			"targetId" : "strings_internal::@cadd5db28f0587d4097f",
			"targetIndex" : 252,
			"type" : "target"
		},
		{
			"backtrace" : 15,
			"component" : "Unspecified",
			"destination" : "lib/pkgconfig",
			"paths" : 
			[
				"/home/dong/drone_kkk_ws/build/px4/lib/pkgconfig/absl_str_format.pc"
			],
			"type" : "file"
		},
		{
			"backtrace" : 17,
			"component" : "Unspecified",
			"destination" : "lib/pkgconfig",
			"paths" : 
			[
				"/home/dong/drone_kkk_ws/build/px4/lib/pkgconfig/absl_str_format_internal.pc"
			],
			"type" : "file"
		},
		{
			"backtrace" : 18,
			"component" : "Unspecified",
			"destination" : "lib",
			"paths" : 
			[
				"_deps/abseil-cpp-build/absl/strings/libabsl_str_format_internal.a"
			],
			"targetId" : "str_format_internal::@cadd5db28f0587d4097f",
			"targetIndex" : 248,
			"type" : "target"
		},
		{
			"backtrace" : 20,
			"component" : "Unspecified",
			"destination" : "lib/pkgconfig",
			"paths" : 
			[
				"/home/dong/drone_kkk_ws/build/px4/lib/pkgconfig/absl_cord_internal.pc"
			],
			"type" : "file"
		},
		{
			"backtrace" : 21,
			"component" : "Unspecified",
			"destination" : "lib",
			"paths" : 
			[
				"_deps/abseil-cpp-build/absl/strings/libabsl_cord_internal.a"
			],
			"targetId" : "cord_internal::@cadd5db28f0587d4097f",
			"targetIndex" : 66,
			"type" : "target"
		},
		{
			"backtrace" : 23,
			"component" : "Unspecified",
			"destination" : "lib/pkgconfig",
			"paths" : 
			[
				"/home/dong/drone_kkk_ws/build/px4/lib/pkgconfig/absl_cordz_update_tracker.pc"
			],
			"type" : "file"
		},
		{
			"backtrace" : 25,
			"component" : "Unspecified",
			"destination" : "lib/pkgconfig",
			"paths" : 
			[
				"/home/dong/drone_kkk_ws/build/px4/lib/pkgconfig/absl_cordz_functions.pc"
			],
			"type" : "file"
		},
		{
			"backtrace" : 26,
			"component" : "Unspecified",
			"destination" : "lib",
			"paths" : 
			[
				"_deps/abseil-cpp-build/absl/strings/libabsl_cordz_functions.a"
			],
			"targetId" : "cordz_functions::@cadd5db28f0587d4097f",
			"targetIndex" : 67,
			"type" : "target"
		},
		{
			"backtrace" : 28,
			"component" : "Unspecified",
			"destination" : "lib/pkgconfig",
			"paths" : 
			[
				"/home/dong/drone_kkk_ws/build/px4/lib/pkgconfig/absl_cordz_statistics.pc"
			],
			"type" : "file"
		},
		{
			"backtrace" : 30,
			"component" : "Unspecified",
			"destination" : "lib/pkgconfig",
			"paths" : 
			[
				"/home/dong/drone_kkk_ws/build/px4/lib/pkgconfig/absl_cordz_handle.pc"
			],
			"type" : "file"
		},
		{
			"backtrace" : 31,
			"component" : "Unspecified",
			"destination" : "lib",
			"paths" : 
			[
				"_deps/abseil-cpp-build/absl/strings/libabsl_cordz_handle.a"
			],
			"targetId" : "cordz_handle::@cadd5db28f0587d4097f",
			"targetIndex" : 68,
			"type" : "target"
		},
		{
			"backtrace" : 33,
			"component" : "Unspecified",
			"destination" : "lib/pkgconfig",
			"paths" : 
			[
				"/home/dong/drone_kkk_ws/build/px4/lib/pkgconfig/absl_cordz_info.pc"
			],
			"type" : "file"
		},
		{
			"backtrace" : 34,
			"component" : "Unspecified",
			"destination" : "lib",
			"paths" : 
			[
				"_deps/abseil-cpp-build/absl/strings/libabsl_cordz_info.a"
			],
			"targetId" : "cordz_info::@cadd5db28f0587d4097f",
			"targetIndex" : 69,
			"type" : "target"
		},
		{
			"backtrace" : 36,
			"component" : "Unspecified",
			"destination" : "lib/pkgconfig",
			"paths" : 
			[
				"/home/dong/drone_kkk_ws/build/px4/lib/pkgconfig/absl_cordz_sample_token.pc"
			],
			"type" : "file"
		},
		{
			"backtrace" : 37,
			"component" : "Unspecified",
			"destination" : "lib",
			"paths" : 
			[
				"_deps/abseil-cpp-build/absl/strings/libabsl_cordz_sample_token.a"
			],
			"targetId" : "cordz_sample_token::@cadd5db28f0587d4097f",
			"targetIndex" : 70,
			"type" : "target"
		},
		{
			"backtrace" : 39,
			"component" : "Unspecified",
			"destination" : "lib/pkgconfig",
			"paths" : 
			[
				"/home/dong/drone_kkk_ws/build/px4/lib/pkgconfig/absl_cordz_update_scope.pc"
			],
			"type" : "file"
		},
		{
			"backtrace" : 41,
			"component" : "Unspecified",
			"destination" : "lib/pkgconfig",
			"paths" : 
			[
				"/home/dong/drone_kkk_ws/build/px4/lib/pkgconfig/absl_cord.pc"
			],
			"type" : "file"
		},
		{
			"backtrace" : 42,
			"component" : "Unspecified",
			"destination" : "lib",
			"paths" : 
			[
				"_deps/abseil-cpp-build/absl/strings/libabsl_cord.a"
			],
			"targetId" : "cord::@cadd5db28f0587d4097f",
			"targetIndex" : 65,
			"type" : "target"
		}
	],
	"paths" : 
	{
		"build" : "_deps/abseil-cpp-build/absl/strings",
		"source" : "/home/dong/drone_kkk_ws/build/px4/_deps/abseil-cpp-src/absl/strings"
	}
}
